fbref_scraper/FBRef_scraper.py
fbref_scraper/__init__.py
fbref_scraper/package_info.py
fbref_scraper-0.0.2.dist-info/LICENSE
fbref_scraper-0.0.2.dist-info/METADATA
fbref_scraper-0.0.2.dist-info/WHEEL
fbref_scraper-0.0.2.dist-info/top_level.txt
fbref_scraper-0.0.2.dist-info/RECORD
