Metadata-Version: 2.1
Name: fbref-scraper
Version: 0.0.2
Summary: Python package to scrape game and player stats from fbref website
Author-email: Lukas Rücker <ruecker.lukas@gmail.com>
Project-URL: Homepage, https://github.com/lurue101/fbref_scraper
Classifier: Programming Language :: Python :: 3
Classifier: License :: OSI Approved :: MIT License
Classifier: Operating System :: OS Independent
Requires-Python: >=3.7
License-File: LICENSE
Requires-Dist: pandas
Requires-Dist: bs4
Requires-Dist: requests
